pextn/__init__.py
pextn/__main__.py
pextn/consts.py
pextn-0.1.dist-info/LICENSE
pextn-0.1.dist-info/METADATA
pextn-0.1.dist-info/WHEEL
pextn-0.1.dist-info/top_level.txt
pextn-0.1.dist-info/RECORD
